python_codegen/__init__.py
python_codegen-0.1.dist-info/WHEEL
python_codegen-0.1.dist-info/METADATA
python_codegen-0.1.dist-info/RECORD
