Metadata-Version: 2.1
Name: python_codegen
Version: 0.1
Summary: Thin wrapper for generating python code
Home-page: UNKNOWN
License: UNKNOWN
Author: Tony Zhu
Classifier: License :: OSI Approved :: MIT License
